lightspark_crypto/__init__.py
lightspark_crypto/libuniffi_lightspark_crypto.dylib
lightspark_crypto/lightspark_crypto.py
lightspark_crypto_python-0.2.0.dist-info/LICENSE
lightspark_crypto_python-0.2.0.dist-info/METADATA
lightspark_crypto_python-0.2.0.dist-info/WHEEL
lightspark_crypto_python-0.2.0.dist-info/top_level.txt
lightspark_crypto_python-0.2.0.dist-info/RECORD
