Metadata-Version: 2.1
Name: lightspark-crypto-python
Version: 0.2.0
Summary: The Python language bindings for lightspark crypto operations
Home-page: https://github.com/lightsparkdev/lightspark-crypto-uniffi
Author: Lightspark Group, Inc. <info@lightspark.com>
License: Apache 2.0
License-File: LICENSE
